synthetic_data_kit/__init__.py
synthetic_data_kit/cli.py
synthetic_data_kit/config.yaml
synthetic_data_kit/core/__init__.py
synthetic_data_kit/core/context.py
synthetic_data_kit/core/create.py
synthetic_data_kit/core/curate.py
synthetic_data_kit/core/ingest.py
synthetic_data_kit/core/save_as.py
synthetic_data_kit/generators/__init__.py
synthetic_data_kit/generators/cot_generator.py
synthetic_data_kit/generators/qa_generator.py
synthetic_data_kit/generators/vqa_generator.py
synthetic_data_kit/models/__init__.py
synthetic_data_kit/models/llm_client.py
synthetic_data_kit/parsers/__init__.py
synthetic_data_kit/parsers/docx_parser.py
synthetic_data_kit/parsers/html_parser.py
synthetic_data_kit/parsers/pdf_parser.py
synthetic_data_kit/parsers/ppt_parser.py
synthetic_data_kit/parsers/txt_parser.py
synthetic_data_kit/parsers/youtube_parser.py
synthetic_data_kit/server/__init__.py
synthetic_data_kit/server/app.py
synthetic_data_kit/server/templates/base.html
synthetic_data_kit/server/templates/create.html
synthetic_data_kit/server/templates/curate.html
synthetic_data_kit/server/templates/files.html
synthetic_data_kit/server/templates/index.html
synthetic_data_kit/server/templates/ingest.html
synthetic_data_kit/server/templates/upload.html
synthetic_data_kit/server/templates/view_file.html
synthetic_data_kit/utils/__init__.py
synthetic_data_kit/utils/config.py
synthetic_data_kit/utils/format_converter.py
synthetic_data_kit/utils/llm_processing.py
synthetic_data_kit/utils/text.py
synthetic_data_kit-0.0.4.dist-info/METADATA
synthetic_data_kit-0.0.4.dist-info/WHEEL
synthetic_data_kit-0.0.4.dist-info/entry_points.txt
synthetic_data_kit-0.0.4.dist-info/licenses/LICENSE
synthetic_data_kit-0.0.4.dist-info/RECORD
