Metadata-Version: 2.4
Name: synthetic-data-kit
Version: 0.0.4
Summary: Tool for generating high quality Synthetic datasets
Project-URL: Homepage, https://github.com/meta-llama/synthetic-data-kit
Project-URL: Bug Tracker, https://github.com/meta-llama/synthetic-data-kit/issues
Project-URL: Documentation, https://github.com/meta-llama/synthetic-data-kit#readme
Project-URL: Getting Started, https://github.com/meta-llama/synthetic-data-kit/blob/main/getting-started/README.md
Author-email: Sanyam Bhutani <sanyambhutani@meta.com>, Hamid Shojanazeri <hamidnazeri@meta.com>
Maintainer-email: Sanyam Bhutani <sanyambhutani@meta.com>, Hamid Shojanazeri <hamidnazeri@meta.com>
License: MIT
License-File: LICENSE
Keywords: ai,chain-of-thought,dataset-generation,fine-tuning,llama,llm,machine-learning,nlp,reasoning,synthetic-data,tool-use
Classifier: Development Status :: 3 - Alpha
Classifier: Intended Audience :: Developers
Classifier: Intended Audience :: Science/Research
Classifier: License :: OSI Approved :: MIT License
Classifier: Natural Language :: English
Classifier: Programming Language :: Python :: 3
Classifier: Programming Language :: Python :: 3.8
Classifier: Programming Language :: Python :: 3.9
Classifier: Programming Language :: Python :: 3.10
Classifier: Programming Language :: Python :: 3.11
Classifier: Programming Language :: Python :: 3.12
Classifier: Topic :: Scientific/Engineering :: Artificial Intelligence
Classifier: Topic :: Scientific/Engineering :: Information Analysis
Classifier: Topic :: Software Development :: Libraries :: Python Modules
Classifier: Topic :: Text Processing :: Linguistic
Requires-Python: >=3.8
Requires-Dist: bootstrap-flask>=2.2.0
Requires-Dist: datasets>=2.14.0
Requires-Dist: flask-wtf>=1.0.0
Requires-Dist: flask>=2.0.0
Requires-Dist: openai>=1.0.0
Requires-Dist: pdfminer-six>=20221105
Requires-Dist: pydantic>=2.4.0
Requires-Dist: python-docx>=0.8.11
Requires-Dist: python-pptx>=0.6.21
Requires-Dist: pytube>=15.0.0
Requires-Dist: pyyaml>=6.0
Requires-Dist: requests>=2.31.0
Requires-Dist: rich>=13.4.2
Requires-Dist: typer>=0.9.0
